scmrepo/__init__.py
scmrepo/asyn.py
scmrepo/base.py
scmrepo/compat.py
scmrepo/exceptions.py
scmrepo/fs.py
scmrepo/noscm.py
scmrepo/progress.py
scmrepo/py.typed
scmrepo/urls.py
scmrepo/utils.py
scmrepo/git/__init__.py
scmrepo/git/config.py
scmrepo/git/credentials.py
scmrepo/git/objects.py
scmrepo/git/stash.py
scmrepo/git/backend/__init__.py
scmrepo/git/backend/base.py
scmrepo/git/backend/gitpython.py
scmrepo/git/backend/dulwich/__init__.py
scmrepo/git/backend/dulwich/asyncssh_vendor.py
scmrepo/git/backend/dulwich/client.py
scmrepo/git/backend/pygit2/__init__.py
scmrepo/git/backend/pygit2/callbacks.py
scmrepo/git/backend/pygit2/filter.py
scmrepo/git/lfs/__init__.py
scmrepo/git/lfs/client.py
scmrepo/git/lfs/exceptions.py
scmrepo/git/lfs/fetch.py
scmrepo/git/lfs/object.py
scmrepo/git/lfs/pointer.py
scmrepo/git/lfs/progress.py
scmrepo/git/lfs/smudge.py
scmrepo/git/lfs/storage.py
scmrepo-3.6.0.dist-info/licenses/LICENSE
scmrepo-3.6.0.dist-info/METADATA
scmrepo-3.6.0.dist-info/WHEEL
scmrepo-3.6.0.dist-info/top_level.txt
scmrepo-3.6.0.dist-info/RECORD
