Metadata-Version: 2.4
Name: scmrepo
Version: 3.6.0
Summary: scmrepo
Author-email: Treeverse <support@dvc.org>
License-Expression: Apache-2.0
Project-URL: Issues, https://github.com/treeverse/scmrepo/issues
Project-URL: Source, https://github.com/treeverse/scmrepo
Classifier: Programming Language :: Python :: 3
Classifier: Programming Language :: Python :: 3.9
Classifier: Programming Language :: Python :: 3.10
Classifier: Programming Language :: Python :: 3.11
Classifier: Programming Language :: Python :: 3.12
Classifier: Programming Language :: Python :: 3.13
Classifier: Programming Language :: Python :: 3.14
Classifier: Development Status :: 4 - Beta
Requires-Python: >=3.9
License-File: LICENSE
Requires-Dist: gitpython>3
Requires-Dist: dulwich>=0.24.3
Requires-Dist: pygit2>=1.14.0
Requires-Dist: pygtrie>=2.3.2
Requires-Dist: fsspec[tqdm]>=2024.2.0
Requires-Dist: pathspec>=0.9.0
Requires-Dist: asyncssh<3,>=2.13.1
Requires-Dist: funcy>=1.14; python_version < "3.12"
Requires-Dist: aiohttp-retry>=2.5.0
Requires-Dist: tqdm
Provides-Extra: tests
Requires-Dist: aioresponses<0.8,>=0.7; extra == "tests"
Requires-Dist: paramiko<5,>=3.4.0; extra == "tests"
Requires-Dist: pytest<9,>=7; extra == "tests"
Requires-Dist: pytest-asyncio<2,>=0.23.2; extra == "tests"
Requires-Dist: pytest-cov>=4.1.0; extra == "tests"
Requires-Dist: pytest-docker<4,>=1; extra == "tests"
Requires-Dist: pytest-mock; extra == "tests"
Requires-Dist: proxy.py; extra == "tests"
Provides-Extra: dev
Requires-Dist: mypy==1.19.1; extra == "dev"
Requires-Dist: scmrepo[tests]; extra == "dev"
Requires-Dist: types-certifi; extra == "dev"
Requires-Dist: types-mock; extra == "dev"
Requires-Dist: types-paramiko; extra == "dev"
Requires-Dist: types-tqdm; extra == "dev"
Dynamic: license-file
